fibonacci/__init__.py
fibonacci/fibonacci.py
package_fib-1.0.0.dist-info/METADATA
package_fib-1.0.0.dist-info/WHEEL
package_fib-1.0.0.dist-info/top_level.txt
package_fib-1.0.0.dist-info/RECORD
